pysublime.py
pysublime-0.1.1.dist-info/licenses/LICENSE
pysublime-0.1.1.dist-info/METADATA
pysublime-0.1.1.dist-info/WHEEL
pysublime-0.1.1.dist-info/top_level.txt
pysublime-0.1.1.dist-info/RECORD
