Metadata-Version: 2.4
Name: pysublime
Version: 0.1.1
Summary: Line-level code embeddings with smart segmentation and negative prompting
Author-email: Daniel Losey <danieljlosey@gmail.com>
License: MIT
Project-URL: Homepage, https://github.com/dadukhankevin/Sublime
Requires-Python: >=3.9
License-File: LICENSE
Requires-Dist: sentence-transformers>=2.2.0
Requires-Dist: faiss-cpu>=1.7.0
Requires-Dist: scikit-learn>=1.0.0
Requires-Dist: watchdog>=2.1.0
Requires-Dist: numpy>=1.21.0
Requires-Dist: torch>=1.9.0
Dynamic: license-file
